jwt_oauth2-0.1.1.dist-info/DESCRIPTION.rst
jwt_oauth2-0.1.1.dist-info/METADATA
jwt_oauth2-0.1.1.dist-info/RECORD
jwt_oauth2-0.1.1.dist-info/WHEEL
jwt_oauth2-0.1.1.dist-info/metadata.json
jwt_oauth2-0.1.1.dist-info/top_level.txt
jwt_oauth2lib/__init__.py
jwt_oauth2lib/rfc7523/__init__.py
jwt_oauth2lib/rfc7523/errors.py
jwt_oauth2lib/rfc7523/request_validator.py
jwt_oauth2lib/rfc7523/clients/__init__.py
jwt_oauth2lib/rfc7523/clients/assertion_validator.py
jwt_oauth2lib/rfc7523/clients/jwt_grant_client.py
jwt_oauth2lib/rfc7523/endpoints/__init__.py
jwt_oauth2lib/rfc7523/endpoints/pre_configured.py
jwt_oauth2lib/rfc7523/grant_types/__init__.py
jwt_oauth2lib/rfc7523/grant_types/jwt_grant.py
oauth2_jwt_provider/__init__.py
oauth2_jwt_provider/apps.py
oauth2_jwt_provider/forms.py
oauth2_jwt_provider/models.py
oauth2_jwt_provider/oauth2_validators.py
oauth2_jwt_provider/settings.py
oauth2_jwt_provider/urls.py
oauth2_jwt_provider/validators.py
oauth2_jwt_provider/views.py
oauth2_jwt_provider/management/__init__.py
oauth2_jwt_provider/management/commands/__init__.py
oauth2_jwt_provider/management/commands/_private.py
oauth2_jwt_provider/management/commands/add_application.py
oauth2_jwt_provider/management/commands/add_to_developers.py
oauth2_jwt_provider/management/commands/add_to_trusted.py
oauth2_jwt_provider/management/commands/allow_skip_authorization.py
oauth2_jwt_provider/management/commands/revoke_skip_authorization.py
oauth2_jwt_provider/migrations/0001_initial.py
oauth2_jwt_provider/migrations/0002_dev_group.py
oauth2_jwt_provider/migrations/__init__.py
tests/__init__.py
tests/models.py
tests/helpers/__init__.py
tests/helpers/fake_token.py
tests/helpers/helpers.py
tests/jwt_oauth2lib/__init__.py
tests/jwt_oauth2lib/rfc7523/__init__.py
tests/jwt_oauth2lib/rfc7523/test_request_validator.py
tests/jwt_oauth2lib/rfc7523/clients/__init__.py
tests/jwt_oauth2lib/rfc7523/clients/test_assertion_validator.py
tests/jwt_oauth2lib/rfc7523/clients/test_jwt_grant_request.py
tests/jwt_oauth2lib/rfc7523/endpoints/__init__.py
tests/jwt_oauth2lib/rfc7523/endpoints/test_pre_configured.py
tests/jwt_oauth2lib/rfc7523/grant_types/__init__.py
